README.md
pytest_serverless.py
pytest_serverless-1.0.0.dist-info/entry_points.txt
pytest_serverless-1.0.0.dist-info/LICENSE
pytest_serverless-1.0.0.dist-info/WHEEL
pytest_serverless-1.0.0.dist-info/METADATA
pytest_serverless-1.0.0.dist-info/RECORD
