Metadata-Version: 2.1
Name: pytest-serverless
Version: 1.0.0
Summary: Automatically mocks resources from serverless.yml in pytest using moto.
Home-page: https://github.com/whisller/pytest-serverless
License: MIT
Keywords: pytest,serverless,moto,boto3
Author: Daniel Ancuta
Author-email: whisller@gmail.com
Requires-Python: >=3.7,<4.0
Classifier: Development Status :: 4 - Beta
Classifier: Intended Audience :: Developers
Classifier: License :: OSI Approved :: MIT License
Classifier: Programming Language :: Python
Classifier: Programming Language :: Python :: 3
Classifier: Programming Language :: Python :: 3 :: Only
Classifier: Programming Language :: Python :: 3.7
Classifier: Programming Language :: Python :: 3.8
Classifier: Programming Language :: Python :: 3.9
Classifier: Topic :: Software Development :: Libraries
Classifier: Topic :: Software Development :: Testing
Classifier: Topic :: Software Development :: Testing :: Mocking
Classifier: Topic :: Software Development :: Testing :: Unit
Requires-Dist: boto3 (>=1.22,<2.0)
Requires-Dist: moto (>=3.1,<4.0)
Requires-Dist: pyyaml (>=6.0,<7.0)
Project-URL: Repository, https://github.com/whisller/pytest-serverless
